{
  "id": "s1034",
  "prim": false,
  "type": "article",
  "cite": null,
  "old_cites": null,
  "lbd": "1896",
  "upd": null,
  "size": null,
  "size_unit": null,
  "title": "From a Silver to a Gold Standard in British Honduras",
  "imprint": null,
  "city": null,
  "country": null,
  "author": "A. Moloney",
  "editor": null,
  "journal": "North American Review",
  "vol": "163",
  "iss": "478",
  "catalogue": "http://proxygw.wrlc.org/login?url=https://www.jstor.org/stable/25118701",
  "description": "pp 257–265",
  "versions": [],
  "note": null,
  "url": "http://proxygw.wrlc.org/login?url=https://www.jstor.org/stable/25118701",
  "via": "v-1.4"
}
