{
  "id": "s1620",
  "prim": false,
  "type": "thesis",
  "cite": null,
  "old_cites": null,
  "lbd": "2017",
  "upd": null,
  "size": null,
  "size_unit": null,
  "title": "An investigation into corporate and role identities in international relations : the case of the Belize-Guatemala territorial border dispute",
  "imprint": "PhD thesis for University of York",
  "city": "York",
  "country": "UK",
  "author": "J. A. Coombs",
  "editor": null,
  "journal": null,
  "vol": null,
  "iss": null,
  "catalogue": "https://ethos.bl.uk/OrderDetails.do?uin=uk.bl.ethos.745745",
  "description": null,
  "versions": [],
  "note": "Thesis embargoed until 11 May 2022",
  "url": null,
  "via": "v-1.4"
}
