{
  "id": "s1726",
  "cite": "Reads",
  "old_cites": "Reads / RWJ 1732",
  "iss_vol_start": 1,
  "iss_vol_end": null,
  "type": "serial",
  "prim": null,
  "lbd": "1730",
  "upd": "1761",
  "title": "Read's Weekly Journal or British Gazetteer",
  "description": "issue 1 to [missg] of [missg]",
  "imprint": "London [England] : Printed for J. Read,",
  "catalogue0": "https://hollis.harvard.edu/permalink/f/1s5nto6/01HVD_ALMA512226388990003941",
  "catalogue1": null,
  "catalogue2": null,
  "versions": [],
  "note": "See 'Extract of a Letter from Campeche in the Province of Yucatan, dated Nov. 24' in no 375 for 27 May 1732 p 3 [https://link-gale-com.ezp-prod1.hul.harvard.edu/apps/doc/Z2001242711/BBCN?u=camb55135&sid=bookmark-BBCN&xid=1707dcf8]",
  "via": "harv"
}
