{
  "id": "s1844",
  "cite": "L Zea",
  "old_cites": "L Zea",
  "iss_vol_start": null,
  "iss_vol_end": null,
  "type": "print",
  "prim": null,
  "lbd": "2003",
  "upd": null,
  "title": "Piratas del Caribe y Mar del Sur en el siglo XVI, 1497-1603",
  "description": "vol 1 of 1 / 1st ed",
  "imprint": null,
  "catalogue0": "https://hollis.harvard.edu/permalink/f/1mdq5o5/TN_cdi_globaltitleindex_catalog_53322573",
  "catalogue1": null,
  "catalogue2": null,
  "versions": [],
  "note": "México, D.F: Universidad Nacional Autónoma de México, Dirección General de Estudios de Posgrado, Facultad de Filosofía y Letras, Programa de Posgrado en Estudios Latinoamericanos",
  "via": "harv"
}
