{
  "id": "s1846",
  "cite": null,
  "old_cites": "Reichert bb",
  "iss_vol_start": null,
  "iss_vol_end": null,
  "type": "print",
  "prim": false,
  "lbd": "2013",
  "upd": null,
  "title": "Sobre las olas de un mar plateado: la política defensiva española y el financiamiento militar novohispano en la región del Gran Caribe, 1598-1700",
  "description": "vol 1 of 1 / 1st ed",
  "imprint": null,
  "catalogue0": "http://id.lib.harvard.edu/alma/990142482140203941/catalog",
  "catalogue1": null,
  "catalogue2": null,
  "versions": [],
  "note": "Mérida : Universidad Nacional Autónoma de México, 2013",
  "via": "harv"
}
