{
  "id": "s20",
  "prim": false,
  "type": "article",
  "cite": "Bialuschewski G",
  "old_cites": "Bialuschewski 20",
  "lbd": "2020",
  "upd": null,
  "size": null,
  "size_unit": null,
  "title": "Juan Gallardo: A Native American Buccaneer",
  "imprint": null,
  "city": null,
  "country": null,
  "author": "A. Bialuschewski",
  "editor": null,
  "journal": "Hispanic American Historical Review",
  "vol": "100",
  "iss": "2",
  "catalogue": "http://gw.worldcat.org.proxygw.wrlc.org/oclc/8576364746",
  "description": "pp 233–256",
  "versions": [],
  "note": null,
  "url": "https://doi-org.ezp-prod1.hul.harvard.edu/10.1215/00182168-8178200",
  "via": "v-1.4"
}
{
  "id": "s20",
  "cite": null,
  "old_cites": "Bialuschewski aa / Bialuschewski G / Bialuschewski 20",
  "iss_vol_start": null,
  "iss_vol_end": null,
  "type": "article",
  "prim": false,
  "lbd": "2020",
  "upd": null,
  "title": "Juan Gallardo: A Native American Buccaneer",
  "description": null,
  "imprint": "Hispanic American Historical Review. 100 (2): 233–256",
  "catalogue0": "https://doi.org/10.1215%2F00182168-8178200",
  "catalogue1": null,
  "catalogue2": null,
  "versions": [],
  "note": null,
  "via": "harv"
}
