{
  "id": "s2064",
  "cite": null,
  "old_cites": null,
  "iss_vol_start": null,
  "iss_vol_end": null,
  "type": "print",
  "prim": null,
  "lbd": "2008",
  "upd": null,
  "title": "Defying empire : trading with the enemy in colonial New York",
  "description": "vol 1 of 1 / [missg] ed",
  "imprint": "New Haven, CT: Yale University Press",
  "catalogue0": "http://id.lib.harvard.edu/alma/990117478550203941/catalog",
  "catalogue1": null,
  "catalogue2": null,
  "versions": [],
  "note": null,
  "via": "harv"
}
