{
  "id": "s2208",
  "cite": null,
  "old_cites": null,
  "iss_vol_start": null,
  "iss_vol_end": null,
  "type": "print",
  "prim": null,
  "lbd": "1894",
  "upd": null,
  "title": "Yucatan y Belice. Colección de Documentos Importantes que se refieren al tratado de 8 de julio de 1893, celebrado entre el Sr. Lic. Ignacio Mariscal en representación de México, y Sir Spencer Saint Jhon en representación de la Gran Bretaña",
  "description": "vol 1 of 1 / [missg] ed",
  "imprint": "Mérida : Tipografía de G. Canto Calle de 'Los Novelo'",
  "catalogue0": "https://hdl.handle.net/2027/hvd.32044056069271",
  "catalogue1": null,
  "catalogue2": null,
  "versions": [],
  "note": null,
  "via": "harv"
}
