{
  "id": "s228",
  "prim": false,
  "type": "thesis",
  "cite": "Elliott",
  "old_cites": null,
  "lbd": "1997",
  "upd": null,
  "size": null,
  "size_unit": null,
  "title": "The officers of the irish brigade and the british army, 1789-98",
  "imprint": "PhD thesis for University of Leeds",
  "city": "Leeds",
  "country": "UK",
  "author": "P. Elliott-Wright",
  "editor": null,
  "journal": null,
  "vol": null,
  "iss": null,
  "catalogue": "http://gw.worldcat.org.proxygw.wrlc.org/oclc/1063625917",
  "description": null,
  "versions": [],
  "note": null,
  "url": "http://search.proquest.com.ezp-prod1.hul.harvard.edu/dissertations-theses/officers-irish-brigade-british-army-1789-98/docview/301519802/se-2?accountid=11311",
  "via": "v-1.4"
}
