{
  "id": "s630",
  "prim": false,
  "type": "article",
  "cite": "Lentz",
  "old_cites": null,
  "lbd": "2014",
  "upd": null,
  "size": null,
  "size_unit": null,
  "title": "Black Belizeans and Fugitive Mayas: Interracial Encounters on the Edge of Empire, 1750–1803",
  "imprint": null,
  "city": null,
  "country": null,
  "author": "M. W. Lentz",
  "editor": null,
  "journal": "Americas",
  "vol": "70",
  "iss": "4",
  "catalogue": "http://gw.worldcat.org.proxygw.wrlc.org/oclc/8513194607",
  "description": "pp 645–675",
  "versions": [],
  "note": null,
  "url": "https://hollis.harvard.edu/primo-explore/fulldisplay?docid=TN_cdi_projectmuse_journals_547191_S153362471440001X&context=PC&vid=HVD2&search_scope=everything&tab=everything&lang=en_US",
  "via": "v-1.4"
}
