{
  "id": "s982",
  "prim": true,
  "type": "article",
  "cite": null,
  "old_cites": null,
  "lbd": "1854",
  "upd": null,
  "size": null,
  "size_unit": null,
  "title": "The labour market of British Honduras",
  "imprint": null,
  "city": null,
  "country": null,
  "author": "R. Temple",
  "editor": null,
  "journal": "Journal of the Society of Arts",
  "vol": "2",
  "iss": "96",
  "catalogue": "http://proxygw.wrlc.org/login?url=https://www.jstor.org/stable/23850902",
  "description": "pp 748–749",
  "versions": [],
  "note": null,
  "url": "http://proxygw.wrlc.org/login?url=https://www.jstor.org/stable/23850902",
  "via": "v-1.4"
}
