{
  "id": "c10599",
  "work": {
    "cod": true,
    "cod_n": null,
    "stat": null,
    "stat_n": null
  },
  "cat": {
    "url": "http://pares.mcu.es/ParesBusquedas20/catalogo/description/348124",
    "docs": 1,
    "title": "CARTAS DE AUDIENCIA",
    "scope": "Carta de Jerónimo Chacón Abarca, oidor de la Audiencia de Guatemala.",
    "desc": null,
    "locn": "Guatemala",
    "lbd": "1683-05-30.",
    "upd": null,
    "ref": "GUATEMALA,28,R.2,N.30"
  },
  "data": {
    "mil": false,
    "pir": null,
    "def": null,
    "lit_n": null,
    "codg_n": null,
    "mil_n": "Haçe recuerdo del estado de la çeguera del obispo Dn Juan de ortega Montañes, que es la causa porque esta detenido en Guatemala sin pasar â Mechoacan /v img 4"
  }
}
