{
  "id": "c11592",
  "work": {
    "cod": null,
    "cod_n": null,
    "stat": null,
    "stat_n": null
  },
  "cat": {
    "url": "http://pares.mcu.es/ParesBusquedas20/catalogo/description/351312",
    "docs": 1,
    "title": "ENCOMIENDA DE TOMAS DE VALDES",
    "scope": "Expediente relativo al despacho que pide Tomás de Valdés para suceder en la Encomienda que disfruto su madre en primera vida, siendo por dos vidas. Resuelto",
    "desc": null,
    "locn": null,
    "lbd": "1697-03-04.",
    "upd": null,
    "ref": "GUATEMALA,109,N.4"
  },
  "data": {
    "mil": null,
    "pir": null,
    "def": null,
    "lit_n": null,
    "codg_n": null,
    "mil_n": null
  }
}
