{
  "id": "c11801",
  "work": {
    "cod": null,
    "cod_n": null,
    "stat": null,
    "stat_n": null
  },
  "cat": {
    "url": "http://pares.mcu.es/ParesBusquedas20/catalogo/description/367718",
    "docs": 1,
    "title": "CONFIRMACION DE OFICIO: NICOLAS CASTILLO",
    "scope": "Expediente de Confirmación del oficio de notario y escribano real de Indias a Nicolás Castillo. Resuelto",
    "desc": null,
    "locn": null,
    "lbd": "1700-03-06.",
    "upd": null,
    "ref": "MEXICO,202,N.33"
  },
  "data": {
    "mil": null,
    "pir": null,
    "def": null,
    "lit_n": null,
    "codg_n": null,
    "mil_n": null
  }
}
