{
  "id": "c1195",
  "work": {
    "cod": null,
    "cod_n": null,
    "stat": null,
    "stat_n": null
  },
  "cat": {
    "url": "http://pares.mcu.es/ParesBusquedas20/catalogo/description/362817",
    "docs": 1,
    "title": "Cartas del virrey Payo Enríquez de Ribera",
    "scope": "El Virrey al secretario del Consejo, recibo de varios pliegos del Dr. Juan Cano Sandoval a la maestreescolía de México, y Don Bartolomé de Aguayo a racionero de Puebla. Título de canónigo doctoral de Michoacán a Don Bernardo de Riofrío, y canónigo magistral de México al Dr. Don Ignacio de Hoyos Santillana. 2 fs",
    "desc": null,
    "locn": "México",
    "lbd": "1678-12-18.",
    "upd": null
  },
  "data": {
    "mil": null,
    "pir": null,
    "def": null,
    "lit_n": null,
    "codg_n": null,
    "mil_n": null
  }
}
