{
  "id": "c1353",
  "work": {
    "cod": null,
    "cod_n": null,
    "stat": null,
    "stat_n": null
  },
  "cat": {
    "url": "http://pares.mcu.es/ParesBusquedas20/catalogo/description/362768",
    "docs": 1,
    "title": "Carta del virrey Payo Enríquez de Ribera",
    "scope": "El Virrey a S.M., jubilación para Don Pedro de Cabañas, contador del Tribunal de cuentas. 8 fs",
    "desc": null,
    "locn": "México",
    "lbd": "1676-06-04.",
    "upd": null,
    "ref": "MEXICO,49,N.19"
  },
  "data": {
    "mil": null,
    "pir": null,
    "def": null,
    "lit_n": null,
    "codg_n": null,
    "mil_n": null
  }
}
