{
  "id": "c1420",
  "work": {
    "cod": false,
    "cod_n": "is conf de oficio",
    "stat": null,
    "stat_n": null
  },
  "cat": {
    "url": "http://pares.mcu.es/ParesBusquedas20/catalogo/description/367247",
    "docs": 1,
    "title": "CONFIRMACION DE OFICIO: SANTA MARINA, BERNARDO ANTONIO",
    "scope": "Expediente de Confirmación del oficio de regidor de Nueva Veracruz a Bernardo Antonio Santa María. Resuelto",
    "desc": null,
    "locn": null,
    "lbd": "1675-03-07.",
    "upd": null
  },
  "data": {
    "mil": null,
    "pir": null,
    "def": null,
    "lit_n": null,
    "codg_n": null,
    "mil_n": null
  }
}
