{
  "id": "c1765",
  "work": {
    "cod": null,
    "cod_n": null,
    "stat": null,
    "stat_n": null
  },
  "cat": {
    "url": "http://pares.mcu.es/ParesBusquedas20/catalogo/description/362574",
    "docs": 1,
    "title": "Carta del virrey marqués de Mancera",
    "scope": "Carta del virrey acusando recibo y cumplimiento de las reales Cédulas de 14 de septiembre de 1671 y 14 de mayo de 1672 ordenando que el oidor Ginés Morote, no continúe en el servicio de esta Audiencia. 2 fs. Anejos: 1.- Título de oidor supernumerario de la Audiencia de los Charcas para Ginés Morote, que lo es de México. Madrid, 24-1-1672. 2 fs. 2.- Testimonio de los autos causados en la restitución de su plaza a Ginés Morote, oidor de México. México, 1-7-1673. 8 fs. 3.- Testimonio de haber entrado en la Caja el Oidor Don Ginés Morote, los 730 pesos en que fue condenado. México, 1-7-1673. 4 fs",
    "desc": null,
    "locn": "México",
    "lbd": "1673-06-01.",
    "upd": null
  },
  "data": {
    "mil": null,
    "pir": null,
    "def": null,
    "lit_n": null,
    "codg_n": null,
    "mil_n": null
  }
}
