{
  "id": "c1953",
  "work": {
    "cod": false,
    "cod_n": "is conf de oficio",
    "stat": null,
    "stat_n": null
  },
  "cat": {
    "url": "http://pares.mcu.es/ParesBusquedas20/catalogo/description/367178",
    "docs": 1,
    "title": "CONFIRMACION DE OFICIO: SEBASTIAN ALARCON Y ESPINOSA",
    "scope": "Expediente de Confirmación del oficio de oficial segundo de la contaduría de tributos y servicios reales de la Nueva España a Sebastián Alarcón y Espinosa. Resuelto",
    "desc": null,
    "locn": null,
    "lbd": "1671-10-24.",
    "upd": null,
    "ref": "MEXICO,193,N.25"
  },
  "data": {
    "mil": null,
    "pir": null,
    "def": null,
    "lit_n": null,
    "codg_n": null,
    "mil_n": null
  }
}
