{
  "id": "c2258",
  "work": {
    "cod": null,
    "cod_n": null,
    "stat": null,
    "stat_n": null
  },
  "cat": {
    "url": "http://pares.mcu.es/ParesBusquedas20/catalogo/description/362378",
    "docs": 1,
    "title": "Carta del virrey Antonio Sebastián de Toledo, marqués de Mancera",
    "scope": "El Virrey a S.M., sobre lo procedido de la limosna de la bula de la Santa Cruzada. 2 fs. Anejos:1.- Memorial sobre puntos tocantes a la cobranza y depósito de lo procedido de la limosna de la bula de la Santa Cruzada. México, 7-XII-1670. 6 fs. 2.- Nota de la Secretaría al Marqués de Miranda, que participe al consejo de cruzada lo ejecutado con relación a la cobranza de la limosna de la bula de la Santa Cruzada. Madrid, 31-V-1671. 2 ho. en 4º",
    "desc": null,
    "locn": "México",
    "lbd": "1670-12-06.",
    "upd": null
  },
  "data": {
    "mil": null,
    "pir": null,
    "def": null,
    "lit_n": null,
    "codg_n": null,
    "mil_n": null
  }
}
