{
  "id": "c2350",
  "work": {
    "cod": null,
    "cod_n": null,
    "stat": null,
    "stat_n": null
  },
  "cat": {
    "url": "http://pares.mcu.es/ParesBusquedas20/catalogo/description/362291",
    "docs": 1,
    "title": "Carta del virrey Antonio Sebastián de Toledo, marqués de Mancera",
    "scope": "El Virrey a S.M., pago de lo que se adeuda al Contador Lorenzo de San Millán. 2 fs. Anejo:1.- Consulta que hizo Don Gonzalo Suárez de San Martín al Virrey sobre pagar la deuda que se tenía con el contador San Millán. México, 30-V-1669. 2 fs",
    "desc": null,
    "locn": "México",
    "lbd": "1669-05-30.",
    "upd": null
  },
  "data": {
    "mil": null,
    "pir": null,
    "def": null,
    "lit_n": null,
    "codg_n": null,
    "mil_n": null
  }
}
