{
  "id": "c332",
  "work": {
    "cod": false,
    "cod_n": null,
    "stat": null,
    "stat_n": null
  },
  "cat": {
    "url": "http://pares.mcu.es/ParesBusquedas20/catalogo/description/347375",
    "docs": 1,
    "title": "CARTAS DE AUDIENCIA",
    "scope": "Expediente relativo a la jubilación de Alonso Moratalla Tebar, oidor de la Audiencia de Guatemala.",
    "desc": null,
    "locn": null,
    "lbd": "1649-02-27.",
    "upd": "1651-02-17.",
    "ref": "GUATEMALA,17,R.2,N.14"
  },
  "data": {
    "mil": null,
    "pir": null,
    "def": null,
    "lit_n": null,
    "codg_n": null,
    "mil_n": null
  }
}
