{
  "id": "c3462",
  "work": {
    "cod": false,
    "cod_n": "is conf de encomienda",
    "stat": null,
    "stat_n": null
  },
  "cat": {
    "url": "http://pares.mcu.es/ParesBusquedas20/catalogo/description/369268",
    "docs": 1,
    "title": "CONFIRMACION DE ENCOMIENDA DE TLAPA",
    "scope": "Expediente de Confirmación de Encomienda de Tlapa a Melchora de Muxica y Morga. Resuelto",
    "desc": null,
    "locn": null,
    "lbd": "1657-04-29.",
    "upd": null,
    "ref": "MEXICO,243,N.55"
  },
  "data": {
    "mil": null,
    "pir": null,
    "def": null,
    "lit_n": null,
    "codg_n": null,
    "mil_n": null
  }
}
