{
  "id": "c4125",
  "work": {
    "cod": false,
    "cod_n": "is conf de oficio",
    "stat": null,
    "stat_n": null
  },
  "cat": {
    "url": "http://pares.mcu.es/ParesBusquedas20/catalogo/description/350578",
    "docs": 1,
    "title": "CONFIRMACION DE OFICIO: FRANCISCO DE AYLLON",
    "scope": "Expediente de Confirmación del oficio de regidor de Chiapa a Francisco de Ayllón. Resuelto",
    "desc": null,
    "locn": null,
    "lbd": "1645-04-04.",
    "upd": null,
    "ref": "GUATEMALA,86,N.37"
  },
  "data": {
    "mil": null,
    "pir": null,
    "def": null,
    "lit_n": null,
    "codg_n": null,
    "mil_n": null
  }
}
