{
  "id": "c4262",
  "work": {
    "cod": false,
    "cod_n": "is conf de encomienda",
    "stat": null,
    "stat_n": null
  },
  "cat": {
    "url": "http://pares.mcu.es/ParesBusquedas20/catalogo/description/351112",
    "docs": 1,
    "title": "CONFIRMACION DE ENCOMIENDA DE SOLISTAGUACAN, ETC",
    "scope": "Expediente de Confirmación de Encomienda de Solistaguacan y Comitaguacan en Chiapa a Jacinto de Jauregui y Tovilla. Resuelto",
    "desc": null,
    "locn": null,
    "lbd": "1643-07-17.",
    "upd": null,
    "ref": "GUATEMALA,101,N.35"
  },
  "data": {
    "mil": null,
    "pir": null,
    "def": null,
    "lit_n": null,
    "codg_n": null,
    "mil_n": null
  }
}
