{
  "id": "c4945",
  "work": {
    "cod": false,
    "cod_n": "is conf de encomienda",
    "stat": null,
    "stat_n": null
  },
  "cat": {
    "url": "http://pares.mcu.es/ParesBusquedas20/catalogo/description/369185",
    "docs": 1,
    "title": "CONFIRMACION DE ENCOMIENDA DE MESTITLAN, ETC",
    "scope": "Expediente de confirmación de encomienda de Mestitlán y Chichicastla a Antonia Cueva y Guevara. Resuelto",
    "desc": null,
    "locn": null,
    "lbd": "1633-07-08.",
    "upd": null
  },
  "data": {
    "mil": null,
    "pir": null,
    "def": null,
    "lit_n": null,
    "codg_n": null,
    "mil_n": null
  }
}
