{
  "id": "c5113",
  "work": {
    "cod": false,
    "cod_n": "not digitised",
    "stat": null,
    "stat_n": null
  },
  "cat": {
    "url": "http://pares.mcu.es/ParesBusquedas20/catalogo/description/349631",
    "docs": 1,
    "title": "Cartas de oficiales reales de Guatemala",
    "scope": "Memorial de los oficiales reales de Guatemala, solicitando un lugar preferente en los actos públicos.",
    "desc": null,
    "locn": null,
    "lbd": "1631-04-11.",
    "upd": null
  },
  "data": {
    "mil": null,
    "pir": null,
    "def": null,
    "lit_n": null,
    "codg_n": null,
    "mil_n": null
  }
}
