{
  "id": "c5152",
  "work": {
    "cod": false,
    "cod_n": "is conf de encomienda",
    "stat": null,
    "stat_n": null
  },
  "cat": {
    "url": "http://pares.mcu.es/ParesBusquedas20/catalogo/description/369177",
    "docs": 1,
    "title": "CONFIRMACION DE ENCOMIENDA DE YZTACAMATITLAN",
    "scope": "Expediente de Confirmación de Encomienda de Yztacamatitlan a Francisco López Muñiz. Resuelto",
    "desc": null,
    "locn": null,
    "lbd": "1630-10-29.",
    "upd": null
  },
  "data": {
    "mil": null,
    "pir": null,
    "def": null,
    "lit_n": null,
    "codg_n": null,
    "mil_n": null
  }
}
