{
  "id": "c5376",
  "work": {
    "cod": null,
    "cod_n": null,
    "stat": null,
    "stat_n": null
  },
  "cat": {
    "url": "http://pares.mcu.es/ParesBusquedas20/catalogo/description/364034",
    "docs": 1,
    "title": "CARTAS DE AUDIENCIA",
    "scope": "Copia de carta del virrey de México.",
    "desc": null,
    "locn": "México",
    "lbd": "1602-02-01.",
    "upd": null,
    "ref": "MEXICO,72,R.10,N.136"
  },
  "data": {
    "mil": null,
    "pir": null,
    "def": null,
    "lit_n": null,
    "codg_n": null,
    "mil_n": null
  }
}
