{
  "id": "c5643",
  "work": {
    "cod": null,
    "cod_n": null,
    "stat": null,
    "stat_n": null
  },
  "cat": {
    "url": "http://pares.mcu.es/ParesBusquedas20/catalogo/description/361157",
    "docs": 1,
    "title": "Carta del virrey Gaspar de Zúñiga Acevedo, conde de Monterrey.",
    "scope": "El Virrey a S.M., defensa ante nuevas de corsarios. Relaciones y demarcaciones de la costa del sur. Religiosos a Nuevo México. Artillería. Renuncia del gobernador de la Vizcaya. Casa de aduana de Acapulco. Anclas para Filipinas. Hay duplicado. 9 fs. Anejos: \n1.- Relación y tanteo de las costas que tuvieron las piezas de artillería de la primera y segunda fundición que se hizo en Acapulco. Acapulco, 15.05.1601 y México, 23-VI-1601. 10 fs. 2.- Relación de la artillería que se ha fundido en el cercado de Chapultepec. 20-V-1603. 2 fs. 3.- El presidente de Guatemala escribió al Virrey sobre la toma del puerto de Caballos por el corsario. Guatemala, 11-IV-1603. 2 fs. 4.- Auto de Virrey sobre el socorro de gente y armas que se envió a la flota para que la hiciese guardia hasta La Habana. México, 2-V-1603. 2 fs. 5.- Billetes, peticiones y otros autos, decretos y respuestas originales en razón de la dejación que Don Rodrigo de Vivero, Gobernador de la Vizcaya, hizo de su gobierno. IV a V, 1603. 14 fs. 6.- El Virrey a S.M., capítulos con materias de guerra. México, 28-V-1603. 2 fs",
    "desc": null,
    "locn": "México",
    "lbd": "1603-05-28.",
    "upd": null,
    "ref": "MEXICO,25,N.37"
  },
  "data": {
    "mil": null,
    "pir": null,
    "def": null,
    "lit_n": null,
    "codg_n": null,
    "mil_n": null
  }
}
