{
  "id": "c6271",
  "work": {
    "cod": null,
    "cod_n": null,
    "stat": null,
    "stat_n": null
  },
  "cat": {
    "url": "http://pares.mcu.es/ParesBusquedas20/catalogo/description/347013",
    "docs": 1,
    "title": "CARTAS DE AUDIENCIA",
    "scope": "Carta de Diego de Arredondo Bracamonte, oidor de la Audiencia de Guatemala.",
    "desc": null,
    "locn": "Guatemala",
    "lbd": "1607-04-30.",
    "upd": null,
    "ref": "GUATEMALA,12,R.4,N.40"
  },
  "data": {
    "mil": null,
    "pir": null,
    "def": null,
    "lit_n": null,
    "codg_n": null,
    "mil_n": null
  }
}
