{
  "id": "c6744",
  "work": {
    "cod": null,
    "cod_n": null,
    "stat": null,
    "stat_n": null
  },
  "cat": {
    "url": "http://pares.mcu.es/ParesBusquedas20/catalogo/description/368755",
    "docs": 1,
    "title": "Informaciones: Alonso García de Tapia",
    "scope": "Informaciones de oficio y parte: Alonso García de Tapia, doctor.",
    "desc": null,
    "locn": null,
    "lbd": "1609.",
    "upd": null,
    "ref": "MEXICO,229,N.7"
  },
  "data": {
    "mil": null,
    "pir": null,
    "def": null,
    "lit_n": null,
    "codg_n": null,
    "mil_n": null
  }
}
