{
  "id": "c687",
  "work": {
    "cod": true,
    "cod_n": null,
    "stat": null,
    "stat_n": null
  },
  "cat": {
    "url": "http://pares.mcu.es/ParesBusquedas20/catalogo/description/347735",
    "docs": 1,
    "title": "CARTAS DE AUDIENCIA",
    "scope": "Carta de la Audiencia de Guatemala/.",
    "desc": null,
    "locn": "Guatemala",
    "lbd": "1666-07-28.",
    "upd": null,
    "ref": "GUATEMALA,22,R.1,N.12"
  },
  "data": {
    "mil": false,
    "pir": null,
    "def": null,
    "lit_n": null,
    "codg_n": null,
    "mil_n": "En cedula de 12 de octubre de 665 manda VM a esta Rl aud.a en la ocaçion informe conq autoridad Y ordenes se hiço en estas prov.as el rezello dela moneda de Rl de ados Y sensillos peruleros, que Cantidad se rezello, en q.o año Y dia semando haçer, si tiene en el vtilidad la Rl hacienda, [etc] /v img 1"
  }
}
