{
  "id": "c6940",
  "work": {
    "cod": null,
    "cod_n": null,
    "stat": null,
    "stat_n": null
  },
  "cat": {
    "url": "http://pares.mcu.es/ParesBusquedas20/catalogo/description/366090",
    "docs": 1,
    "title": "CONFIRMACION DE OFICIO: DOMINGO FERNANDEZ FRANCO",
    "scope": "Expediente de Confirmación del oficio de regidor de Nuestra Señora de la Victoria, en Tabasco a Domingo Fernández Franco. Resuelto",
    "desc": null,
    "locn": null,
    "lbd": "1611-04-29.",
    "upd": null,
    "ref": "MEXICO,179,N.8"
  },
  "data": {
    "mil": null,
    "pir": null,
    "def": null,
    "lit_n": null,
    "codg_n": null,
    "mil_n": null
  }
}
