{
  "id": "c7054",
  "work": {
    "cod": null,
    "cod_n": null,
    "stat": null,
    "stat_n": null
  },
  "cat": {
    "url": "http://pares.mcu.es/ParesBusquedas20/catalogo/description/366102",
    "docs": 1,
    "title": "CONFIRMACION DE OFICIO: JUAN CARRILLO ALTAMIRANO",
    "scope": "Expediente de Confirmación del oficio de alguacil mayor de las minas de Talpujagua a Juan Carrillo Altamirano. Resuelto",
    "desc": null,
    "locn": null,
    "lbd": "1612-01-13.",
    "upd": null,
    "ref": "MEXICO,179,N.20"
  },
  "data": {
    "mil": null,
    "pir": null,
    "def": null,
    "lit_n": null,
    "codg_n": null,
    "mil_n": null
  }
}
