{
  "id": "c7223",
  "work": {
    "cod": null,
    "cod_n": null,
    "stat": null,
    "stat_n": null
  },
  "cat": {
    "url": "http://pares.mcu.es/ParesBusquedas20/catalogo/description/366141",
    "docs": 1,
    "title": "CONFIRMACION DE OFICIO: ALONSO ROSADO",
    "scope": "Expediente de Confirmación del oficio de regidor de Yucatán. Resuelto",
    "desc": null,
    "locn": null,
    "lbd": "1613-02-08.",
    "upd": null,
    "ref": "MEXICO,179,N.59"
  },
  "data": {
    "mil": null,
    "pir": null,
    "def": null,
    "lit_n": null,
    "codg_n": null,
    "mil_n": null
  }
}
