{
  "id": "c7568",
  "work": {
    "cod": null,
    "cod_n": null,
    "stat": null,
    "stat_n": null
  },
  "cat": {
    "url": "http://pares.mcu.es/ParesBusquedas20/catalogo/description/350953",
    "docs": 1,
    "title": "CONFIRMACION DE ENCOMIENDA DE IZTACOMICLAN, ETC",
    "scope": "Expediente de Confirmación de Encomienda de Iztacomiclan, Bitilan, Oiezcuatlan, Ocoticlan, Tepiencoapa y Zitalazitaclan en Chiapa a Pedro de Eizaguirre. Resuelto",
    "desc": null,
    "locn": null,
    "lbd": "1615-03-28.",
    "upd": null,
    "ref": "GUATEMALA,97,N.31"
  },
  "data": {
    "mil": null,
    "pir": null,
    "def": null,
    "lit_n": null,
    "codg_n": null,
    "mil_n": null
  }
}
