{
  "id": "c7881",
  "work": {
    "cod": null,
    "cod_n": null,
    "stat": null,
    "stat_n": null
  },
  "cat": {
    "url": "http://pares.mcu.es/ParesBusquedas20/catalogo/description/12783090",
    "docs": 1,
    "title": "Real Cédula a Antonio de Figueroa, gobernador de Yucatán, ordenándole que, si es cierta la relación que los oficiales reales hacen sobre la escusa que el obispo y prebendados de la iglesia de allí dan para no pagar los novenos, haga por enterarse de lo que se debe en la Caja Real.",
    "scope": null,
    "desc": null,
    "locn": "Madrid",
    "lbd": "1617-06-08.",
    "upd": null,
    "ref": "MEXICO,1094,L.19,F.213R"
  },
  "data": {
    "mil": null,
    "pir": null,
    "def": null,
    "lit_n": null,
    "codg_n": null,
    "mil_n": null
  }
}
