{
  "id": "c8138",
  "work": {
    "cod": null,
    "cod_n": null,
    "stat": null,
    "stat_n": null
  },
  "cat": {
    "url": "http://pares.mcu.es/ParesBusquedas20/catalogo/description/12782583",
    "docs": 1,
    "title": "Real Cédula a los gobernadores de los puertos de las Indias y partes donde toque la Flota que ha de ir a Nueva Espala en 1619 al mando de Lope de Hoces y Córdoba, ordenándoles que prevengan y manden lo necesarios para que se provea de bastimentos a precios justos y moderados.",
    "scope": null,
    "desc": null,
    "locn": "Madrid",
    "lbd": "1618-11-10.",
    "upd": null,
    "ref": "MEXICO,1094,L.20,F.111V"
  },
  "data": {
    "mil": null,
    "pir": null,
    "def": null,
    "lit_n": null,
    "codg_n": null,
    "mil_n": null
  }
}
