{
  "id": "c8303",
  "work": {
    "cod": null,
    "cod_n": null,
    "stat": null,
    "stat_n": null
  },
  "cat": {
    "url": "http://pares.mcu.es/ParesBusquedas20/catalogo/description/12783666",
    "docs": 1,
    "title": "Real cédula a Francisco Ramírez Briceño, gobernador de la provincia de Yucatán y a los oficiales reales de la misma, ordenándoles informar sobre lo que pide la Iglesia Catedral de la provincia de Yucatán referente a que los oficiales reales de ella, paguen diezmo de los tributos que cobran a los indios naboría y mulatos, y como sucede con los demás de la provincia que están en la real corona.",
    "scope": null,
    "desc": null,
    "locn": "Lisboa",
    "lbd": "1619-07-28.",
    "upd": null,
    "ref": "MEXICO,1094,L.20,F.189V-190R"
  },
  "data": {
    "mil": null,
    "pir": null,
    "def": null,
    "lit_n": null,
    "codg_n": null,
    "mil_n": null
  }
}
