{
  "id": "c8586",
  "work": {
    "cod": null,
    "cod_n": null,
    "stat": null,
    "stat_n": null
  },
  "cat": {
    "url": "http://pares.mcu.es/ParesBusquedas20/catalogo/description/12821046",
    "docs": 1,
    "title": "Real cédula a [Juan Pérez de la Serna], arzobispo de México, para que informe sobre la petición del deán y cabildo de la catedral de Mérida de Yucatán, acerca de que el obispo de dicha provincia guarde la forma acostumbrada en el rezo de los maitines por los prebendados, igual que se le ordenó por cédula de 17 de noviembre de 1618 al obispo de Panamá.",
    "scope": null,
    "desc": null,
    "locn": "Madrid",
    "lbd": "1621-05-11.",
    "upd": null,
    "ref": "MEXICO,1094,L.21,F.89V-90R"
  },
  "data": {
    "mil": null,
    "pir": null,
    "def": null,
    "lit_n": null,
    "codg_n": null,
    "mil_n": null
  }
}
