{
  "id": "c8634",
  "work": {
    "cod": null,
    "cod_n": null,
    "stat": null,
    "stat_n": null
  },
  "cat": {
    "url": "http://pares.mcu.es/ParesBusquedas20/catalogo/description/12876240",
    "docs": 1,
    "title": "Real cédula concediendo licencia a [Juan de Salinas], gobernador de la Florida, y a los oficiales del presidio [de San Agustín], para que puedan llevar dos piezas de bronce de 80 quintales, desde el presidio a la fundición de la isla de Cuba, a fin de que se saquen de ellas cuatro piezas de 20 quintales cada una, corriendo los gastos por cuenta de la Real Hacienda.",
    "scope": null,
    "desc": null,
    "locn": "Madrid",
    "lbd": "1621-08-14.",
    "upd": null,
    "ref": "MEXICO,1094,L.21,F.113V-114V"
  },
  "data": {
    "mil": null,
    "pir": null,
    "def": null,
    "lit_n": null,
    "codg_n": null,
    "mil_n": null
  }
}
