{
  "id": "c8925",
  "work": {
    "cod": null,
    "cod_n": null,
    "stat": null,
    "stat_n": null
  },
  "cat": {
    "url": "http://pares.mcu.es/ParesBusquedas20/catalogo/description/3629367",
    "docs": 1,
    "title": "Inventario de bienes: Palenzuela y Zurbarán, Bernardino",
    "scope": "Autos del inventario de bienes de Bernardino de Palenzuela y Zurbarán, vecino de México y escribano real. \nActuados ante Gonzalo de Carvajal, corregidor de la ciudad de México.",
    "desc": ". Folios 549-550",
    "locn": null,
    "lbd": "1622-07-16",
    "upd": null,
    "ref": "MEXICO,259,N.195"
  },
  "data": {
    "mil": null,
    "pir": null,
    "def": null,
    "lit_n": null,
    "codg_n": null,
    "mil_n": null
  }
}
