{
  "id": "c9678",
  "work": {
    "cod": null,
    "cod_n": null,
    "stat": null,
    "stat_n": null
  },
  "cat": {
    "url": "http://pares.mcu.es/ParesBusquedas20/catalogo/description/3543588",
    "docs": 1,
    "title": "Inventario de bienes: Campuzano Barrionuevo, Matías de",
    "scope": "Autos del inventario de bienes de Matías de Campuzano Barrionuevo, alguacil mayor de las Minas de Zultepec y su jurisdicción. \nActuados ante Juan de Ontiveros Nava, justicia mayor de las Minas de Zultepec.",
    "desc": ". Folios 122-124",
    "locn": null,
    "lbd": "1622-08-16",
    "upd": null,
    "ref": "MEXICO,259,N.45"
  },
  "data": {
    "mil": null,
    "pir": null,
    "def": null,
    "lit_n": null,
    "codg_n": null,
    "mil_n": null
  }
}
